lamb/__init__.py
lamb/auto.py
lamb/combinators.py
lamb/console.py
lamb/display.py
lamb/lang.py
lamb/lnsetup.py
lamb/magics.py
lamb/parsing.py
lamb/test_lang.py
lamb/tree_mini.py
lamb/treetransforms.py
lamb/types.py
lamb/utils.py
lamb/meta/__init__.py
lamb/meta/boolean.py
lamb/meta/core.py
lamb/meta/meta.py
lamb/meta/number.py
lamb/meta/parser.py
lamb/meta/ply.py
lamb/meta/quantifiers.py
lamb/meta/sets.py
lamb/meta/test.py
lamb/notebooks/An introduction to compositionality.ipynb
lamb/notebooks/Introduction to typed lambda calculus.ipynb
lamb/notebooks/Lambda Notebook Intro (start here).ipynb
lamb/notebooks/documentation/Ad hoc polymorphism.ipynb
lamb/notebooks/documentation/Binding expressions.ipynb
lamb/notebooks/documentation/Composition.ipynb
lamb/notebooks/documentation/Domain elements and MetaTerms.ipynb
lamb/notebooks/documentation/Intro to type variables.ipynb
lamb/notebooks/documentation/Lexical ambiguity.ipynb
lamb/notebooks/documentation/Metalanguage documentation.ipynb
lamb/notebooks/documentation/Metalanguage evaluation.ipynb
lamb/notebooks/documentation/Metalanguage functions.ipynb
lamb/notebooks/documentation/Metalanguage sets.ipynb
lamb/notebooks/documentation/Partiality documentation.ipynb
lamb/notebooks/documentation/Quick reference.ipynb
lamb/notebooks/fragments/Compositional DRT.ipynb
lamb/notebooks/fragments/Continuations and quantifier scope.ipynb
lamb/notebooks/fragments/Hamblin semantics.ipynb
lamb/notebooks/fragments/Intensional scope.ipynb
lamb/notebooks/fragments/Neo-davidsonian event semantics.ipynb
lamb/notebooks/fragments/Reader monad demo.ipynb
lamb/notebooks/fragments/Relative clauses.ipynb
lamb/notebooks/fragments/Variable free binding.ipynb
lamb/notebooks/fragments/von Fintel and Heim beginning.ipynb
lamb/notebooks/misc/00 Readme for upgrading from IPython 2.ipynb
lamb/notebooks/misc/Diagnostics.ipynb
lamb/notebooks/misc/LSA poster examples.ipynb
lamb/notebooks/misc/Lambda calculus testing.ipynb
lambda_notebook-0.8.0.dist-info/licenses/LICENSE
lambda_notebook-0.8.0.dist-info/METADATA
lambda_notebook-0.8.0.dist-info/WHEEL
lambda_notebook-0.8.0.dist-info/top_level.txt
lambda_notebook-0.8.0.dist-info/RECORD
