Metadata-Version: 2.4
Name: lambda-notebook
Version: 0.8.0
Summary: Tools for linguistic semantics (lambda calculus, logic, etc), aimed at Jupyter
Home-page: https://github.com/rawlins/lambda-notebook/
Author: Kyle Rawlins
Author-email: kgr@jhu.edu
License: BSD-3-Clause
Project-URL: Documentation, https://rawlins.github.io/lambda-notebook/
Project-URL: Changelog, https://rawlins.github.io/lambda-notebook/CHANGELOG.html
Classifier: Development Status :: 4 - Beta
Classifier: Intended Audience :: Science/Research
Classifier: Topic :: Scientific/Engineering :: Visualization
Classifier: Topic :: Text Processing :: Linguistic
Classifier: Framework :: Jupyter
Classifier: Environment :: Web Environment
Requires-Python: >=3.10
License-File: LICENSE
Requires-Dist: svgling>=0.3
Requires-Dist: jupyter
Requires-Dist: traitlets>=5.0.0
Provides-Extra: dev
Requires-Dist: nb-clean; extra == "dev"
Dynamic: license-file
